sapphire/README.md
sapphire/__init__.py
sapphire/api.py
sapphire/clusters.py
sapphire/esd.py
sapphire/kascade.py
sapphire/publicdb.py
sapphire/qsub.py
sapphire/storage.py
sapphire/time_util.py
sapphire/utils.py
sapphire/analysis/__init__.py
sapphire/analysis/calibration.py
sapphire/analysis/coincidence_queries.py
sapphire/analysis/coincidences.py
sapphire/analysis/core_reconstruction.py
sapphire/analysis/direction_reconstruction.py
sapphire/analysis/event_utils.py
sapphire/analysis/find_mpv.py
sapphire/analysis/landau.py
sapphire/analysis/process_events.py
sapphire/analysis/process_traces.py
sapphire/analysis/reconstructions.py
sapphire/analysis/time_deltas.py
sapphire/corsika/LICENSE
sapphire/corsika/README.md
sapphire/corsika/__init__.py
sapphire/corsika/blocks.py
sapphire/corsika/corsika_queries.py
sapphire/corsika/generate_corsika_overview.py
sapphire/corsika/mergesort.py
sapphire/corsika/particles.py
sapphire/corsika/qsub_corsika.py
sapphire/corsika/qsub_store_corsika_data.py
sapphire/corsika/reader.py
sapphire/corsika/store_corsika_data.py
sapphire/corsika/units.py
sapphire/data/__init__.py
sapphire/data/clusters.json
sapphire/data/countries.json
sapphire/data/extend_local_data.py
sapphire/data/stations.json
sapphire/data/subclusters.json
sapphire/data/update_local_data.py
sapphire/data/clusters/0.json
sapphire/data/clusters/1000.json
sapphire/data/clusters/11000.json
sapphire/data/clusters/12000.json
sapphire/data/clusters/13000.json
sapphire/data/clusters/14000.json
sapphire/data/clusters/15000.json
sapphire/data/clusters/16000.json
sapphire/data/clusters/17000.json
sapphire/data/clusters/2000.json
sapphire/data/clusters/20000.json
sapphire/data/clusters/3000.json
sapphire/data/clusters/4000.json
sapphire/data/clusters/40000.json
sapphire/data/clusters/50000.json
sapphire/data/clusters/60000.json
sapphire/data/clusters/7000.json
sapphire/data/clusters/70000.json
sapphire/data/clusters/8000.json
sapphire/data/countries/0.json
hisparc_sapphire-3.1.0.dist-info/entry_points.txt
hisparc_sapphire-3.1.0.dist-info/LICENSE
hisparc_sapphire-3.1.0.dist-info/WHEEL
hisparc_sapphire-3.1.0.dist-info/METADATA
hisparc_sapphire-3.1.0.dist-info/RECORD
