Metadata-Version: 2.1
Name: hisparc-sapphire
Version: 3.1.0
Summary: A framework for the HiSPARC experiment
Keywords: cosmic rays,detectors,astrophysics,HiSPARC,Nikhef,University of Utah
Author: David Fokkema, Tom Kooij
Author-email: Arne de Laat <arne@delaat.net>
Maintainer-email: Arne de Laat <arne@delaat.net>
Requires-Python: >=3.9
Classifier: Intended Audience :: Education
Classifier: Intended Audience :: Science/Research
Classifier: License :: OSI Approved :: GNU General Public License v3 (GPLv3)
Classifier: Operating System :: OS Independent
Classifier: Programming Language :: Python :: 3
Classifier: Programming Language :: Python
Classifier: Topic :: Education
Classifier: Topic :: Scientific/Engineering
Requires-Dist: numpy>=1.25.2
Requires-Dist: scipy>=1.13.0
Requires-Dist: tables>=3.9.2
Requires-Dist: progressbar2>=4.4.2
Requires-Dist: astropy>=5.0.0 ; extra == "astropy"
Requires-Dist: Sphinx ; extra == "dev"
Requires-Dist: coverage==7.5.4 ; extra == "dev"
Requires-Dist: ruff==0.5.1 ; extra == "dev"
Requires-Dist: flit==3.9.0 ; extra == "publish"
Project-URL: Documentation, https://docs.hisparc.nl/sapphire/
Project-URL: Homepage, https://data.hisparc.nl
Project-URL: Issues, https://github.com/HiSPARC/sapphire/issues
Project-URL: Repository, https://github.com/hisparc/sapphire/
Provides-Extra: astropy
Provides-Extra: dev
Provides-Extra: publish
